yodapa/__init__.py
yodapa/core/__init__.py
yodapa/core/config.py
yodapa/core/plugin.py
yodapa/core/util.py
yodapa/plugins/__init__.py
yodapa/plugins/ai.py
yodapa/plugins/bye.py
yodapa/plugins/dev.py
yodapa/plugins/hi.py
yodapa/plugins/url.py
yodapa/yoda.py
yodapa-2.0.2.dist-info/METADATA
yodapa-2.0.2.dist-info/WHEEL
yodapa-2.0.2.dist-info/entry_points.txt
yodapa-2.0.2.dist-info/RECORD
