Metadata-Version: 2.1
Name: yodapa
Version: 2.0.2
Summary: Personal Assistant on the command line
Home-page: https://yoda-pa.github.io/yoda
License: MIT
Author: Man Parvesh Singh Randhawa
Author-email: manparveshsinghrandhawa@gmail.com
Requires-Python: >=3.9,<4.0
Classifier: License :: OSI Approved :: MIT License
Classifier: Programming Language :: Python :: 3
Classifier: Programming Language :: Python :: 3.9
Classifier: Programming Language :: Python :: 3.10
Classifier: Programming Language :: Python :: 3.11
Classifier: Programming Language :: Python :: 3.12
Requires-Dist: fastapi[standard] (>=0.115.0,<0.116.0)
Requires-Dist: mkdocs (>=1.6.1,<2.0.0)
Requires-Dist: mkdocs-material (>=9.5.39,<10.0.0)
Requires-Dist: ollama (>=0.3.3,<0.4.0)
Requires-Dist: python-whois (>=0.9.4,<0.10.0)
Requires-Dist: pyyaml (>=6.0.2,<7.0.0)
Requires-Dist: requests (>=2.32.3,<3.0.0)
Requires-Dist: speedtest-cli (>=2.1.3,<3.0.0)
Requires-Dist: sqlmodel (>=0.0.22,<0.0.23)
Requires-Dist: supervisor (>=4.2.5,<5.0.0)
Requires-Dist: typer (>=0.12.5,<0.13.0)
Requires-Dist: uvicorn[standard] (>=0.31.1,<0.32.0)
Project-URL: Repository, https://github.com/yoda-pa/yoda/tree/v2
